linode_mgmt/LINODE-MGMT_VERSION
linode_mgmt/__init__.py
linode_mgmt/args.py
linode_mgmt/linode_mgmt.py
linode_mgmt/scripts/linode-mgmt
linode_mgmt-0.0.7.data/data/docs/linode_mgmt/README.md
linode_mgmt-0.0.7.data/scripts/linode-mgmt
linode_mgmt-0.0.7.dist-info/METADATA
linode_mgmt-0.0.7.dist-info/WHEEL
linode_mgmt-0.0.7.dist-info/top_level.txt
linode_mgmt-0.0.7.dist-info/RECORD
