Metadata-Version: 2.1
Name: linode_mgmt
Version: 0.0.7
Summary: Linode management python package
Home-page: 
Author: Shlomi Ben-David
Author-email: shlomi.ben.david@gmail.com
Classifier: Programming Language :: Python :: 3.9
Classifier: License :: OSI Approved :: MIT License
Classifier: Operating System :: OS Independent
Requires-Python: >=3.9
Requires-Dist: certifi ==2023.7.22
Requires-Dist: charset-normalizer ==3.3.0
Requires-Dist: idna ==3.4
Requires-Dist: linode-api4 ==5.9.0
Requires-Dist: polling ==0.3.2
Requires-Dist: pylib3 ==0.0.4
Requires-Dist: requests ==2.31.0
Requires-Dist: termcolor ==1.1.0
Requires-Dist: urllib3 ==2.0.6
